arborium/__init__.py
arborium/visualizer.py
arborium/visualizer_templates.py
arborium-0.1.5.dist-info/LICENSE
arborium-0.1.5.dist-info/METADATA
arborium-0.1.5.dist-info/WHEEL
arborium-0.1.5.dist-info/top_level.txt
arborium-0.1.5.dist-info/RECORD
